<?xml version="1.0" encoding="utf-8" ?>
<dwsync>
<file name="scorpion.jpg" server="sanzoid.zxq.net" local="130540580700123096" remote="130540879200000000" Dst="2" />
<file name="flash.jpg" server="sanzoid.zxq.net" local="130540582731899307" remote="130540879200000000" Dst="2" />
<file name="gotham.png" server="sanzoid.zxq.net" local="130540570444916531" remote="130540879200000000" Dst="2" />
<file name="shield.jpg" server="sanzoid.zxq.net" local="130540585058342372" remote="130540879200000000" Dst="2" />
<file name="marryme.jpg" server="sanzoid.zxq.net" local="130540585387831217" remote="130540879200000000" Dst="2" />
<file name="mindyproject.jpg" server="sanzoid.zxq.net" local="130540637030044983" remote="130540879200000000" Dst="2" />
<file name="forever.jpg" server="sanzoid.zxq.net" local="130540588097626209" remote="130540879200000000" Dst="2" />
<file name="mysteriesoflaura.jpg" server="sanzoid.zxq.net" local="130540583226137575" remote="130540879800000000" Dst="2" />
<file name="samaritan.png" server="sanzoid.zxq.net" local="130540722381476806" remote="130540879800000000" Dst="2" />
<file name="redbandsociety.jpg" server="sanzoid.zxq.net" local="130540585644395892" remote="130540879800000000" Dst="2" />
<file name="modernfamily.jpg" server="sanzoid.zxq.net" local="130540585815055653" remote="130540879800000000" Dst="2" />
<file name="personofinterest.png" server="sanzoid.zxq.net" local="130540587783578246" remote="130540879800000000" Dst="2" />
<file name="arrow.jpg" server="sanzoid.zxq.net" local="130540583469091472" remote="130540879800000000" Dst="2" />
<file name="greysanatomy.jpg" server="sanzoid.zxq.net" local="130540583963379743" remote="130540879800000000" Dst="2" />
<file name="black-ish.jpg" server="sanzoid.zxq.net" local="130540586981962396" remote="130540879800000000" Dst="2" />
<file name="scandal.jpg" server="sanzoid.zxq.net" local="130540586291012876" remote="130540879800000000" Dst="2" />
<file name="badjudge.jpg" server="sanzoid.zxq.net" local="130540584799667576" remote="130540879800000000" Dst="2" />
<file name="elementary.jpg" server="sanzoid.zxq.net" local="130540588295357518" remote="130540879800000000" Dst="2" />
<file name="howtogetawaywithmurder.jpg" server="sanzoid.zxq.net" local="130540588572163351" remote="130540879800000000" Dst="2" />
<file name="atoz.jpg" server="sanzoid.zxq.net" local="130540587268478784" remote="130540879800000000" Dst="2" />
<file name="constantine.jpg" server="sanzoid.zxq.net" local="130540588842358805" remote="130540879800000000" Dst="2" />
<file name="cristela.jpg" server="sanzoid.zxq.net" local="130540596910000248" remote="130540879800000000" Dst="2" />
<file name="grimm.jpg" server="sanzoid.zxq.net" local="130540586473423310" remote="130540879800000000" Dst="2" />
<file name="ouat.jpg" server="sanzoid.zxq.net" local="130540584243455763" remote="130540879800000000" Dst="2" />
<file name="madamsecretary.jpg" server="sanzoid.zxq.net" local="130540584571044500" remote="130540880400000000" Dst="2" />
</dwsync>